nanoleafeffects/__init__.py
nanoleafeffects/generator.py
nanoleafeffects/schema.py
nanoleafeffects-0.1.0.dist-info/licenses/LICENSE
nanoleafeffects-0.1.0.dist-info/METADATA
nanoleafeffects-0.1.0.dist-info/WHEEL
nanoleafeffects-0.1.0.dist-info/top_level.txt
nanoleafeffects-0.1.0.dist-info/RECORD
