Metadata-Version: 2.4
Name: nanoleafeffects
Version: 0.1.0
Summary: Generate Nanoleaf light effects.
Requires-Python: >=3.13
License-File: LICENSE
Requires-Dist: google-genai>=1.49.0
Requires-Dist: pydantic>=2.12.4
Dynamic: license-file
